{
  "measuredAt": "2026-07-14T04:15:36.436Z",
  "gitCommit": "ba1648bd365a5242cc0dcde33c4e2313a0684f25",
  "gitWorkingTree": [],
  "options": {
    "url": "http://127.0.0.1:4173/?seed=7&slots=24&q=0&m=1&dpr=1&probe=1",
    "warmupSeconds": 15,
    "measureSeconds": 30,
    "rounds": 5,
    "viewportWidth": 1440,
    "viewportHeight": 727,
    "chromePath": "/Applications/Google Chrome.app/Contents/MacOS/Google Chrome"
  },
  "environment": {
    "userAgent": "Mozilla/5.0 (Macintosh; Intel Mac OS X 10_15_7) AppleWebKit/537.36 (KHTML, like Gecko) HeadlessChrome/150.0.0.0 Safari/537.36",
    "viewport": {
      "innerWidth": 1440,
      "innerHeight": 727,
      "devicePixelRatio": 2,
      "canvasClientWidth": 1440,
      "canvasClientHeight": 727,
      "drawingBufferWidth": 1440,
      "drawingBufferHeight": 727
    },
    "webgl": {
      "vendor": "Google Inc. (Apple)",
      "renderer": "ANGLE (Apple, ANGLE Metal Renderer: Apple M1, Unspecified Version)"
    }
  },
  "medianOfRoundSummaries": {
    "frameMs": {
      "count": 1800,
      "min": 14.60000000000582,
      "p50": 16.69999999999709,
      "p95": 18.20000000001164,
      "p99": 18.59999999999127,
      "max": 18.79999999998836,
      "mean": 16.666611111111123
    },
    "updateMs": {
      "count": 1800,
      "min": 0.19999998807907104,
      "p50": 0.800000011920929,
      "p95": 1.399999976158142,
      "p99": 1.7000000476837158,
      "max": 3.099999964237213,
      "mean": 0.861555555595292
    },
    "drawCalls": {
      "count": 1800,
      "min": 27,
      "p50": 28,
      "p95": 29,
      "p99": 29,
      "max": 31,
      "mean": 28.030555555555555
    },
    "instancedDrawCalls": {
      "count": 1800,
      "min": 11,
      "p50": 11,
      "p95": 11,
      "p99": 12,
      "max": 13,
      "mean": 11.030555555555555
    },
    "submittedVertices": {
      "count": 1800,
      "min": 491370,
      "p50": 499746,
      "p95": 510774,
      "p99": 524202,
      "max": 524226,
      "mean": 500895.2033333333
    },
    "bufferSubDataBytes": {
      "count": 1800,
      "min": 23424,
      "p50": 26336,
      "p95": 29456,
      "p99": 30416,
      "max": 33968,
      "mean": 26202.65777777778
    },
    "uniform4fvBytes": {
      "count": 1800,
      "min": 8960,
      "p50": 8960,
      "p95": 8960,
      "p99": 8960,
      "max": 8960,
      "mean": 8960
    },
    "gpuMs": {
      "count": 1800,
      "min": 5.243458,
      "p50": 12.355125,
      "p95": 19.818208,
      "p99": 24.656416,
      "max": 27.954583,
      "mean": 12.852245942190102
    }
  },
  "rounds": [
    {
      "frameMs": {
        "count": 1800,
        "min": 15.5,
        "p50": 16.69999999999709,
        "p95": 17.400000000001455,
        "p99": 17.600000000002183,
        "max": 17.700000000004366,
        "mean": 16.666388888888882
      },
      "updateMs": {
        "count": 1800,
        "min": 0.30000001192092896,
        "p50": 1,
        "p95": 1.5,
        "p99": 1.800000011920929,
        "max": 3.099999964237213,
        "mean": 1.0003333344724443
      },
      "drawCalls": {
        "count": 1800,
        "min": 27,
        "p50": 28,
        "p95": 29,
        "p99": 29,
        "max": 31,
        "mean": 28.030555555555555
      },
      "instancedDrawCalls": {
        "count": 1800,
        "min": 11,
        "p50": 11,
        "p95": 11,
        "p99": 12,
        "max": 13,
        "mean": 11.030555555555555
      },
      "submittedVertices": {
        "count": 1800,
        "min": 492030,
        "p50": 499746,
        "p95": 503496,
        "p99": 524202,
        "max": 524226,
        "mean": 500895.2033333333
      },
      "bufferSubDataBytes": {
        "count": 1800,
        "min": 31456,
        "p50": 32720,
        "p95": 33776,
        "p99": 33904,
        "max": 33968,
        "mean": 32781.41777777778
      },
      "uniform4fvBytes": {
        "count": 1800,
        "min": 8960,
        "p50": 8960,
        "p95": 8960,
        "p99": 8960,
        "max": 8960,
        "mean": 8960
      },
      "gpuMs": {
        "count": 1800,
        "min": 5.534416,
        "p50": 12.611916,
        "p95": 20.11875,
        "p99": 25.107374,
        "max": 35.385416,
        "mean": 13.37434412611113
      },
      "gpuTimerAvailable": true,
      "gpuQueriesPending": 0,
      "gpuDisjointSamples": 0
    },
    {
      "frameMs": {
        "count": 1800,
        "min": 14.900000000001455,
        "p50": 16.69999999999709,
        "p95": 17.400000000001455,
        "p99": 17.599999999998545,
        "max": 18.5,
        "mean": 16.66616666666667
      },
      "updateMs": {
        "count": 1800,
        "min": 0.30000001192092896,
        "p50": 1,
        "p95": 1.4000000357627869,
        "p99": 1.800000011920929,
        "max": 10.300000011920929,
        "mean": 0.9693888890080982
      },
      "drawCalls": {
        "count": 1800,
        "min": 27,
        "p50": 28,
        "p95": 28,
        "p99": 28,
        "max": 29,
        "mean": 28
      },
      "instancedDrawCalls": {
        "count": 1800,
        "min": 11,
        "p50": 11,
        "p95": 11,
        "p99": 11,
        "max": 11,
        "mean": 11
      },
      "submittedVertices": {
        "count": 1800,
        "min": 491694,
        "p50": 503046,
        "p95": 510774,
        "p99": 510852,
        "max": 510876,
        "mean": 502051.12333333335
      },
      "bufferSubDataBytes": {
        "count": 1800,
        "min": 27872,
        "p50": 30352,
        "p95": 32336,
        "p99": 33072,
        "max": 33232,
        "mean": 30346.08
      },
      "uniform4fvBytes": {
        "count": 1800,
        "min": 8960,
        "p50": 8960,
        "p95": 8960,
        "p99": 8960,
        "max": 8960,
        "mean": 8960
      },
      "gpuMs": {
        "count": 1799,
        "min": 4.507333,
        "p50": 12.770708,
        "p95": 20.462333,
        "p99": 25.229624,
        "max": 26.80425,
        "mean": 13.44247590717064
      },
      "gpuTimerAvailable": true,
      "gpuQueriesPending": 1,
      "gpuDisjointSamples": 0
    },
    {
      "frameMs": {
        "count": 1800,
        "min": 14.599999999991269,
        "p50": 16.69999999999709,
        "p95": 18.20000000001164,
        "p99": 18.59999999999127,
        "max": 18.79999999998836,
        "mean": 16.666833333333336
      },
      "updateMs": {
        "count": 1800,
        "min": 0.19999998807907104,
        "p50": 0.800000011920929,
        "p95": 1.399999976158142,
        "p99": 1.7000000476837158,
        "max": 2.700000047683716,
        "mean": 0.861555555595292
      },
      "drawCalls": {
        "count": 1800,
        "min": 27,
        "p50": 28,
        "p95": 29,
        "p99": 29,
        "max": 29,
        "mean": 28
      },
      "instancedDrawCalls": {
        "count": 1800,
        "min": 11,
        "p50": 11,
        "p95": 11,
        "p99": 11,
        "max": 11,
        "mean": 11
      },
      "submittedVertices": {
        "count": 1800,
        "min": 491370,
        "p50": 491709,
        "p95": 510162,
        "p99": 510177,
        "max": 510192,
        "mean": 496670.55
      },
      "bufferSubDataBytes": {
        "count": 1800,
        "min": 23424,
        "p50": 26336,
        "p95": 29456,
        "p99": 29744,
        "max": 29968,
        "mean": 26202.65777777778
      },
      "uniform4fvBytes": {
        "count": 1800,
        "min": 8960,
        "p50": 8960,
        "p95": 8960,
        "p99": 8960,
        "max": 8960,
        "mean": 8960
      },
      "gpuMs": {
        "count": 1799,
        "min": 5.243458,
        "p50": 12.355125,
        "p95": 19.818208,
        "p99": 24.647958,
        "max": 35.465916,
        "mean": 12.852245942190102
      },
      "gpuTimerAvailable": true,
      "gpuQueriesPending": 1,
      "gpuDisjointSamples": 0
    },
    {
      "frameMs": {
        "count": 1801,
        "min": 14.599999999991269,
        "p50": 16.69999999999709,
        "p95": 18.30000000000291,
        "p99": 18.60000000000582,
        "max": 18.79999999998836,
        "mean": 16.66746252082176
      },
      "updateMs": {
        "count": 1801,
        "min": 0.19999998807907104,
        "p50": 0.800000011920929,
        "p95": 1.300000011920929,
        "p99": 1.600000023841858,
        "max": 2.5,
        "mean": 0.8384230991061167
      },
      "drawCalls": {
        "count": 1801,
        "min": 27,
        "p50": 28,
        "p95": 29,
        "p99": 30,
        "max": 31,
        "mean": 28.20599666851749
      },
      "instancedDrawCalls": {
        "count": 1801,
        "min": 11,
        "p50": 11,
        "p95": 12,
        "p99": 12,
        "max": 13,
        "mean": 11.205441421432537
      },
      "submittedVertices": {
        "count": 1801,
        "min": 479268,
        "p50": 497907,
        "p95": 526179,
        "p99": 526272,
        "max": 526299,
        "mean": 499967.45530260965
      },
      "bufferSubDataBytes": {
        "count": 1801,
        "min": 12784,
        "p50": 18288,
        "p95": 23664,
        "p99": 23872,
        "max": 196320,
        "mean": 19308.686285397
      },
      "uniform4fvBytes": {
        "count": 1801,
        "min": 8960,
        "p50": 8960,
        "p95": 8960,
        "p99": 8960,
        "max": 8960,
        "mean": 8960
      },
      "gpuMs": {
        "count": 1800,
        "min": 5.569083,
        "p50": 12.264749,
        "p95": 19.437708,
        "p99": 24.656416,
        "max": 27.954583,
        "mean": 12.750706899999992
      },
      "gpuTimerAvailable": true,
      "gpuQueriesPending": 1,
      "gpuDisjointSamples": 0
    },
    {
      "frameMs": {
        "count": 1800,
        "min": 14.60000000000582,
        "p50": 16.699999999982538,
        "p95": 18.29999999998836,
        "p99": 18.60000000000582,
        "max": 18.79999999998836,
        "mean": 16.666611111111123
      },
      "updateMs": {
        "count": 1800,
        "min": 0.19999998807907104,
        "p50": 0.800000011920929,
        "p95": 1.300000011920929,
        "p99": 1.600000023841858,
        "max": 8.899999976158142,
        "mean": 0.8283333324061499
      },
      "drawCalls": {
        "count": 1800,
        "min": 27,
        "p50": 29,
        "p95": 30,
        "p99": 31,
        "max": 31,
        "mean": 28.755555555555556
      },
      "instancedDrawCalls": {
        "count": 1800,
        "min": 11,
        "p50": 12,
        "p95": 13,
        "p99": 13,
        "max": 13,
        "mean": 11.755555555555556
      },
      "submittedVertices": {
        "count": 1800,
        "min": 479928,
        "p50": 518790,
        "p95": 526134,
        "p99": 526212,
        "max": 526224,
        "mean": 511317.7133333333
      },
      "bufferSubDataBytes": {
        "count": 1800,
        "min": 11184,
        "p50": 19648,
        "p95": 28336,
        "p99": 30416,
        "max": 206744,
        "mean": 21062.426666666666
      },
      "uniform4fvBytes": {
        "count": 1800,
        "min": 8960,
        "p50": 8960,
        "p95": 8960,
        "p99": 8960,
        "max": 8960,
        "mean": 8960
      },
      "gpuMs": {
        "count": 1800,
        "min": 4.898666,
        "p50": 11.629208,
        "p95": 19.399541,
        "p99": 23.634125,
        "max": 26.183,
        "mean": 12.259026976111109
      },
      "gpuTimerAvailable": true,
      "gpuQueriesPending": 0,
      "gpuDisjointSamples": 0
    }
  ]
}
